meta_sites/__init__.py
meta_sites/apps.py
meta_sites/models.py
meta_sites/sites.py
meta_sites/tests/__init__.py
meta_sites/tests/test_sites.py
meta_sites/tests/urls.py
meta_sites-0.1.2.dist-info/AUTHORS
meta_sites-0.1.2.dist-info/LICENSE
meta_sites-0.1.2.dist-info/METADATA
meta_sites-0.1.2.dist-info/WHEEL
meta_sites-0.1.2.dist-info/top_level.txt
meta_sites-0.1.2.dist-info/RECORD
